claude_pilot/__init__.py
claude_pilot/__main__.py
claude_pilot/assets.py
claude_pilot/build_hook.py
claude_pilot/cli.py
claude_pilot/codex.py
claude_pilot/config.py
claude_pilot/initializer.py
claude_pilot/updater.py
claude_pilot-4.0.5.data/data/claude_pilot/.claude/.pilot-version
claude_pilot-4.0.5.data/data/claude_pilot/.claude/settings.default.json
claude_pilot-4.0.5.data/data/claude_pilot/.claude/settings.json
claude_pilot-4.0.5.data/data/claude_pilot/.claude/settings.json.package
claude_pilot-4.0.5.data/data/claude_pilot/.claude/settings.local.json
claude_pilot-4.0.5.data/data/claude_pilot/.claude/agents/CONTEXT.md
claude_pilot-4.0.5.data/data/claude_pilot/.claude/agents/code-reviewer.md
claude_pilot-4.0.5.data/data/claude_pilot/.claude/agents/coder.md
claude_pilot-4.0.5.data/data/claude_pilot/.claude/agents/documenter.md
claude_pilot-4.0.5.data/data/claude_pilot/.claude/agents/explorer.md
claude_pilot-4.0.5.data/data/claude_pilot/.claude/agents/plan-reviewer.md
claude_pilot-4.0.5.data/data/claude_pilot/.claude/agents/researcher.md
claude_pilot-4.0.5.data/data/claude_pilot/.claude/agents/tester.md
claude_pilot-4.0.5.data/data/claude_pilot/.claude/agents/validator.md
claude_pilot-4.0.5.data/data/claude_pilot/.claude/commands/00_plan.md
claude_pilot-4.0.5.data/data/claude_pilot/.claude/commands/01_confirm.md
claude_pilot-4.0.5.data/data/claude_pilot/.claude/commands/02_execute.md
claude_pilot-4.0.5.data/data/claude_pilot/.claude/commands/03_close.md
claude_pilot-4.0.5.data/data/claude_pilot/.claude/commands/90_review.md
claude_pilot-4.0.5.data/data/claude_pilot/.claude/commands/91_document.md
claude_pilot-4.0.5.data/data/claude_pilot/.claude/commands/92_init.md
claude_pilot-4.0.5.data/data/claude_pilot/.claude/commands/CONTEXT.md
claude_pilot-4.0.5.data/data/claude_pilot/.claude/guides/3tier-documentation.md
claude_pilot-4.0.5.data/data/claude_pilot/.claude/guides/CONTEXT.md
claude_pilot-4.0.5.data/data/claude_pilot/.claude/guides/claude-code-standards.md
claude_pilot-4.0.5.dist-info/METADATA
claude_pilot-4.0.5.dist-info/WHEEL
claude_pilot-4.0.5.dist-info/entry_points.txt
claude_pilot-4.0.5.dist-info/licenses/LICENSE
claude_pilot-4.0.5.dist-info/RECORD
