Metadata-Version: 2.4
Name: claude-pilot
Version: 4.0.5
Summary: Claude Code CLI Pilot - Your development workflow companion
Project-URL: Homepage, https://github.com/changoo89/claude-pilot
Project-URL: Repository, https://github.com/changoo89/claude-pilot
Project-URL: Issues, https://github.com/changoo89/claude-pilot/issues
Author-email: changoo89 <noreply@example.com>
License: MIT
License-File: LICENSE
Keywords: claude,cli,development,workflow
Classifier: Development Status :: 4 - Beta
Classifier: Intended Audience :: Developers
Classifier: License :: OSI Approved :: MIT License
Classifier: Programming Language :: Python :: 3
Classifier: Programming Language :: Python :: 3.9
Classifier: Programming Language :: Python :: 3.10
Classifier: Programming Language :: Python :: 3.11
Classifier: Programming Language :: Python :: 3.12
Classifier: Programming Language :: Python :: 3.13
Requires-Python: >=3.9
Requires-Dist: click>=8.1.0
Requires-Dist: questionary>=2.0.0
Requires-Dist: requests>=2.28.0
Requires-Dist: rich>=13.0.0
Provides-Extra: dev
Requires-Dist: mypy>=1.0.0; extra == 'dev'
Requires-Dist: pytest-cov>=4.0.0; extra == 'dev'
Requires-Dist: pytest>=7.0.0; extra == 'dev'
Requires-Dist: ruff>=0.1.0; extra == 'dev'
